py_tailwind_utils/__init__.py
py_tailwind_utils/colors.py
py_tailwind_utils/common.py
py_tailwind_utils/dpathutils.py
py_tailwind_utils/modifiers.py
py_tailwind_utils/palette-v2x.json
py_tailwind_utils/styClause.py
py_tailwind_utils/style_tags.py
py_tailwind_utils/style_values.py
py_tailwind_utils/style_values_noop.py
py_tailwind_utils/utils.py
py_tailwind_utils/valuetags.py
py_tailwind_utils-1.1.1.dist-info/LICENSE
py_tailwind_utils-1.1.1.dist-info/WHEEL
py_tailwind_utils-1.1.1.dist-info/METADATA
py_tailwind_utils-1.1.1.dist-info/RECORD
