Metadata-Version: 2.1
Name: py-tailwind-utils
Version: 1.1.1
Summary: tailwind utility classes as first class python objects
Maintainer-email: Kabira K <kabira@monallabs.in>
Requires-Python: >=3.11
Requires-Dist: addict-tracking-changes==1.0.6
Requires-Dist: json-fix==0.5.2
Requires-Dist: dpath==2.1.6
Requires-Dist: aenum==3.1.15
Project-URL: Documentation, https://monallabs-org.github.io/py-tailwind-utils
Project-URL: Home, https://webworks.monallabs.in/ofjustpy/addict-tracking-changes
Project-URL: Source, https://github.com/monallabs-org/py-tailwind-utils
